process_dcm/__init__.py
process_dcm/__main__.py
process_dcm/const.py
process_dcm/main.py
process_dcm/utils.py
process_dcm-0.10.0.dist-info/LICENSE
process_dcm-0.10.0.dist-info/METADATA
process_dcm-0.10.0.dist-info/WHEEL
process_dcm-0.10.0.dist-info/entry_points.txt
process_dcm-0.10.0.dist-info/RECORD
