Metadata-Version: 2.3
Name: process-dcm
Version: 0.10.0
Summary: Python library and app to extract images from DCM in a JSON-based standard format
License: MIT
Author: Alan Silva
Author-email: 3899850+alanwilter@users.noreply.github.com
Requires-Python: >=3.10,<4.0
Classifier: Programming Language :: Python :: 3
Classifier: License :: OSI Approved :: MIT License
Classifier: Operating System :: OS Independent
Requires-Dist: opencv-python-headless (>=4.12.0.88)
Requires-Dist: pillow (>=11.3.0)
Requires-Dist: pydicom (>=3.0.1)
Requires-Dist: python-gdcm (>=3.0.25)
Requires-Dist: typer (>=0.16.0)
Project-URL: Repository, https://github.com/pontikos-lab/process-dcm
